pyrdawos/__init__.py
pyrdawos/mapper.py
pyrdawos-0.0.1.dist-info/METADATA
pyrdawos-0.0.1.dist-info/WHEEL
pyrdawos-0.0.1.dist-info/top_level.txt
pyrdawos-0.0.1.dist-info/RECORD
